README.rst
setup.py
wronganswer/__init__.py
wronganswer/__main__.py
wronganswer/asm.py
wronganswer/command.py
wronganswer/credential.py
wronganswer/http.py
wronganswer/image.py
wronganswer/judge.py
wronganswer/profile.py
wronganswer/project.py
wronganswer/runner.py
wronganswer/subprocess.py
wronganswer/task.py
wronganswer/utils.py
wronganswer.egg-info/PKG-INFO
wronganswer.egg-info/SOURCES.txt
wronganswer.egg-info/dependency_links.txt
wronganswer.egg-info/entry_points.txt
wronganswer.egg-info/requires.txt
wronganswer.egg-info/top_level.txt
wronganswer/agent/__init__.py
wronganswer/agent/local.py
wronganswer/agent/vjudge.py
wronganswer/cache/__init__.py
wronganswer/cache/github.py
wronganswer/cache/user.py
wronganswer/cache/zip.py
wronganswer/client/AOJ.py
wronganswer/client/LC.py
wronganswer/client/POJ.py
wronganswer/client/__init__.py
wronganswer/state/__init__.py
wronganswer/state/dbm.py
wronganswer/state/user.py