Metadata-Version: 1.1
Name: wronganswer
Version: 0.1.12
Summary: online judge clients
Home-page: https://github.com/bhuztez/wronganswer
Author: bhuztez
Author-email: bhuztez@gmail.com
License: MIT
Platform: UNKNOWN
Classifier: Development Status :: 2 - Pre-Alpha
Classifier: Environment :: Console
Classifier: License :: OSI Approved :: MIT License
Classifier: Operating System :: POSIX :: Linux
Classifier: Operating System :: Microsoft :: Windows
Classifier: Operating System :: MacOS :: MacOS X
Classifier: Programming Language :: Python :: 3.7
Classifier: Programming Language :: Python :: 3 :: Only
